abxvs3d/__init__.py
abxvs3d/main.py
abxvs3d-0.2.0.dist-info/METADATA
abxvs3d-0.2.0.dist-info/WHEEL
abxvs3d-0.2.0.dist-info/top_level.txt
abxvs3d-0.2.0.dist-info/RECORD
