Metadata-Version: 2.1
Name: abxvs3d
Version: 0.2.0
Summary: A test library for my research work
Home-page: https://github.com/yourusername/your-repo-name
Author: Juned Inamdar
Author-email: jinamdar4433@gmail.com
Classifier: Programming Language :: Python :: 3
Classifier: License :: OSI Approved :: MIT License
Classifier: Operating System :: OS Independent
Requires-Python: >=3.6
